agentfoundry/__init__.py
agentfoundry/__main__.cpython-312-x86_64-linux-gnu.so
agentfoundry/__main__.py
agentfoundry/agentfoundry.lic
agentfoundry/agentfoundry.pem
agentfoundry/bootstrap.cpython-312-x86_64-linux-gnu.so
agentfoundry/bootstrap.py
agentfoundry/discovery.cpython-312-x86_64-linux-gnu.so
agentfoundry/discovery.py
agentfoundry/goal_manager.cpython-312-x86_64-linux-gnu.so
agentfoundry/goal_manager.py
agentfoundry/agents/__init__.py
agentfoundry/agents/architect.cpython-312-x86_64-linux-gnu.so
agentfoundry/agents/architect.py
agentfoundry/agents/autogen_hierarchical.cpython-312-x86_64-linux-gnu.so
agentfoundry/agents/autogen_hierarchical.py
agentfoundry/agents/base_agent.cpython-312-x86_64-linux-gnu.so
agentfoundry/agents/base_agent.py
agentfoundry/agents/orchestrator.cpython-312-x86_64-linux-gnu.so
agentfoundry/agents/orchestrator.py
agentfoundry/agents/prompt_factory.cpython-312-x86_64-linux-gnu.so
agentfoundry/agents/prompt_factory.py
agentfoundry/agents/memory/base_memory.cpython-312-x86_64-linux-gnu.so
agentfoundry/agents/memory/base_memory.py
agentfoundry/agents/memory/constants.cpython-312-x86_64-linux-gnu.so
agentfoundry/agents/memory/constants.py
agentfoundry/agents/memory/global_memory.cpython-312-x86_64-linux-gnu.so
agentfoundry/agents/memory/global_memory.py
agentfoundry/agents/memory/manager.cpython-312-x86_64-linux-gnu.so
agentfoundry/agents/memory/manager.py
agentfoundry/agents/memory/org_memory.cpython-312-x86_64-linux-gnu.so
agentfoundry/agents/memory/org_memory.py
agentfoundry/agents/memory/summary_utils.cpython-312-x86_64-linux-gnu.so
agentfoundry/agents/memory/summary_utils.py
agentfoundry/agents/memory/thread_manager.cpython-312-x86_64-linux-gnu.so
agentfoundry/agents/memory/thread_manager.py
agentfoundry/agents/memory/thread_memory.cpython-312-x86_64-linux-gnu.so
agentfoundry/agents/memory/thread_memory.py
agentfoundry/agents/memory/types.cpython-312-x86_64-linux-gnu.so
agentfoundry-1.4.13.dist-info/METADATA
agentfoundry-1.4.13.dist-info/WHEEL
agentfoundry-1.4.13.dist-info/top_level.txt
agentfoundry-1.4.13.dist-info/RECORD
agentfoundry-1.4.13.dist-info/licenses/LICENSE
