Metadata-Version: 2.4
Name: agentfoundry
Version: 1.4.13
Summary: AgentFoundry: A modular autonomous AI agent framework
Author-email: Chris Steel <csteel@syntheticore.com>
License-Expression: LicenseRef-Proprietary
Classifier: Programming Language :: Python :: 3.11
Classifier: Operating System :: OS Independent
Requires-Python: >=3.11
License-File: LICENSE
Requires-Dist: langchain>=0.1.0
Requires-Dist: langchain_community>=0.1.0
Requires-Dist: langchain_core>=0.1.0
Requires-Dist: langchain_google_genai>=0.1.0
Requires-Dist: langchain-milvus>=0.1.0
Requires-Dist: langchain_ollama>=0.1.0
Requires-Dist: langchain_openai>=0.1.0
Requires-Dist: langchain_xai>=0.1.0
Requires-Dist: langgraph>=0.1.0
Requires-Dist: openai>=1.0.0
Requires-Dist: duckdb>=0.9.0
Requires-Dist: beautifulsoup4>=4.12.0
Requires-Dist: pdfkit>=1.0.0
Requires-Dist: pypdf>=3.0.0
Requires-Dist: pandas>=1.5.0
Requires-Dist: pyodbc>=4.0.0
Requires-Dist: adbc_driver_manager>=0.8.0
Requires-Dist: pydantic>=2.0.0
Requires-Dist: requests>=2.31.0
Requires-Dist: jinja2>=3.1.0
Requires-Dist: markdown>=3.4.0
Requires-Dist: markdown-it-py<4.0.0,>=1.0.0
Requires-Dist: cryptography>=41.0.0
Requires-Dist: google_search_results>=2.4.0
Requires-Dist: toml>=0.10.0
Requires-Dist: idna
Requires-Dist: importlib_metadata>=6.8.0
Requires-Dist: packaging
Requires-Dist: pygments
Requires-Dist: requests
Requires-Dist: requests_toolbelt
Requires-Dist: pytz>=2023.3
Requires-Dist: setuptools>=68.0.0
Requires-Dist: typing_extensions>=4.7.0
Requires-Dist: wheel
Requires-Dist: awscli
Requires-Dist: fastapi>=0.110.0
Requires-Dist: uvicorn[standard]>=0.23.0
Dynamic: license-file
Dynamic: requires-dist
